funman/__init__.py
funman/_version.py
funman/constants.py
funman/funman.py
funman/api/__init__.py
funman/api/api.py
funman/api/client.py
funman/api/server.py
funman/model/__init__.py
funman/model/bilayer.py
funman/model/decapode.py
funman/model/encoded.py
funman/model/gromet.py
funman/model/model.py
funman/model/query.py
funman/model/simulator.py
funman/representation/__init__.py
funman/representation/representation.py
funman/scenario/__init__.py
funman/scenario/consistency.py
funman/scenario/parameter_synthesis.py
funman/scenario/scenario.py
funman/scenario/simulation.py
funman/search/__init__.py
funman/search/box_search.py
funman/search/search.py
funman/search/smt_check.py
funman/translate/__init__.py
funman/translate/bilayer.py
funman/translate/decapode.py
funman/translate/encoded.py
funman/translate/gromet.py
funman/translate/translate.py
funman/utils/__init__.py
funman/utils/handlers.py
funman/utils/math_utils.py
funman/utils/smtlib_utils.py
funman-1.5.0.dist-info/LICENSE
funman-1.5.0.dist-info/METADATA
funman-1.5.0.dist-info/WHEEL
funman-1.5.0.dist-info/top_level.txt
funman-1.5.0.dist-info/RECORD
