Metadata-Version: 2.1
Name: funman
Version: 1.5.0
Summary: Functional Model Analysis Tool
Home-page: 
Author: Dan Bryce
Author-email: dbryce@sift.net
License: MIT
License-File: LICENSE
Requires-Dist: graphviz
Requires-Dist: multiprocess
Requires-Dist: tenacity
Requires-Dist: pyparsing
Requires-Dist: pysmt
Requires-Dist: pandas
Requires-Dist: matplotlib
Provides-Extra: dreal
Requires-Dist: funman-dreal ; extra == 'dreal'
